pyshortio/__init__.py
pyshortio/_version.py
pyshortio/api.py
pyshortio/arg.py
pyshortio/client.py
pyshortio/constants.py
pyshortio/docs/__init__.py
pyshortio/domain.py
pyshortio/exc.py
pyshortio/export.py
pyshortio/link_management.py
pyshortio/link_queries.py
pyshortio/logger.py
pyshortio/model.py
pyshortio/paginator.py
pyshortio/paths.py
pyshortio/sync_tsv.py
pyshortio/tests/__init__.py
pyshortio/tests/client.py
pyshortio/tests/helper.py
pyshortio/type_hint.py
pyshortio/utils.py
pyshortio/vendor/__init__.py
pyshortio/vendor/pytest_cov_helper.py
pyshortio/vendor/vislog.py
pyshortio-0.3.1.dist-info/AUTHORS.rst
pyshortio-0.3.1.dist-info/LICENSE.txt
pyshortio-0.3.1.dist-info/METADATA
pyshortio-0.3.1.dist-info/WHEEL
pyshortio-0.3.1.dist-info/RECORD
